requestsocket/__init__.py
requestsocket/errors.py
requestsocket/socketrequests_.py
requestsocket/socketsession.py
requestsocket/test.py
requestsocket/types_.py
requestsocket/utils.py
socketrequest/__init__.py
socketrequest/errors.py
socketrequest/socketrequests_.py
socketrequest/socketsession.py
socketrequest/test.py
socketrequest/types_.py
socketrequest/utils.py
requestsocket-0.0.1.dist-info/LICENSE
requestsocket-0.0.1.dist-info/METADATA
requestsocket-0.0.1.dist-info/WHEEL
requestsocket-0.0.1.dist-info/top_level.txt
requestsocket-0.0.1.dist-info/RECORD
